Anime3rbDL/__init__.py
Anime3rbDL/__main__.py
Anime3rbDL/bot.py
Anime3rbDL/client.py
Anime3rbDL/config.py
Anime3rbDL/downloader.py
Anime3rbDL/enums.py
Anime3rbDL/exceptions.py
Anime3rbDL/logger.py
Anime3rbDL/parser.py
anime3rbdl-1.0.8.dist-info/licenses/LICENSE
anime3rbdl-1.0.8.dist-info/METADATA
anime3rbdl-1.0.8.dist-info/WHEEL
anime3rbdl-1.0.8.dist-info/entry_points.txt
anime3rbdl-1.0.8.dist-info/top_level.txt
anime3rbdl-1.0.8.dist-info/RECORD
