Metadata-Version: 2.4
Name: Anime3rbDL
Version: 1.0.8
Summary: Anime3rbDL is a robust, feature-rich command-line application designed for anime enthusiasts. It enables seamless searching, browsing, and downloading of high-quality anime episodes directly from the Anime3rb platform. Featuring advanced logging capabilities, customizable color output, multi-resolution support, batch downloading, and comprehensive CLI options, it provides a powerful yet user-friendly experience for managing anime collections efficiently.
Home-page: https://github.com/Jo0X01/Anime3rbDL
Author: Jo0x01
License: MIT
Keywords: anime,downloader,cli,Anime3rb,video,download,logging,scraper,automation,command-line,python,episodes,series,entertainment,media,streaming,batch-download,high-quality,fast,reliable,color-output,multi-resolution,anime-collection,media-downloader,web-scraper,terminal-tool,open-source
Classifier: Development Status :: 4 - Beta
Classifier: Programming Language :: Python :: 3
Classifier: License :: OSI Approved :: MIT License
Classifier: Operating System :: OS Independent
Classifier: Topic :: Internet :: WWW/HTTP
Classifier: Topic :: Multimedia :: Video
Requires-Python: >=3.8
License-File: LICENSE
Requires-Dist: beautifulsoup4==4.13.5
Requires-Dist: cloudscraper==1.2.71
Requires-Dist: fake-useragent>=0.1.11
Requires-Dist: pydoll-python==2.8.0
Requires-Dist: psutil>=7.1.0
Dynamic: author
Dynamic: classifier
Dynamic: description
Dynamic: description-content-type
Dynamic: home-page
Dynamic: keywords
Dynamic: license
Dynamic: license-file
Dynamic: requires-dist
Dynamic: requires-python
Dynamic: summary
